{
 "nom": "\"Base\" indicateurs de rémunération sur objectifs de santé publique (ROSP)",
"gestionnaire": "CNAMTS",
"commentaire": "Ensemble des médecins libéraux, sauf ceux qui ont fait connaître leur refus avant le 26 décembre 2011. Le dispositif concerne l’ensemble des médecins, généralistes et spécialistes. Cette base Qualité fait partie de la catégorie Qualité du Ministère des Affaires sociales, de la Santé et des Droits des femmes.",
"alimentation": "Médecins libéraux",
"description": "29 indicateurs",
"lien": "http://www.ameli.fr/fileadmin/user_upload/documents/DP_Bilan_ROSP_1_an_11042013_VDEF3.pdf" 
}
