{
 "nom": "Résultats du contrôle sanitaire de la qualité de l’eau potable",
"gestionnaire": "Ministère des affaires sociales et de la santé",
"commentaire": " Cette base Environnement fait partie de la catégorie Environnement du Ministère des Affaires sociales, de la Santé et des Droits des femmes.",
"description": "Par commune et par prélèvement : dernier prélèvement et valeur de conformité et paramère analytique (ammonium, aspect …)",
"lien": "http://www.sante.gouv.fr/resultats-du-controle-sanitaire-de-la-qualite-de-l-eau-potable.html" 
}
