{
 "nom": "Recueil des bulletins statistiques d'interruptions de grossesse (BIG)",
"gestionnaire": "DREES",
"commentaire": " Cette base Activité des établissements de santé fait partie de la catégorie Activité des établissements de santé du Ministère des Affaires sociales, de la Santé et des Droits des femmes.",
"alimentation": "Déclaration obligatoire",
"description": "Nombre d'IVG au total, par âge, par région, par type d'IVG",
"lien": "http://www.drees.sante.gouv.fr/les-interruptions-volontaires-de-grossesse-en-2010,10978.html" 
}
